bamboo/__init__.py
bamboo/ccp4_utils.py
bamboo/constants.py
bamboo/rcsb_utils.py
bamboo/common/__init__.py
bamboo/common/colours.py
bamboo/common/command.py
bamboo/common/errors.py
bamboo/common/file.py
bamboo/common/holders.py
bamboo/common/logs.py
bamboo/common/masks.py
bamboo/common/online.py
bamboo/common/parser.py
bamboo/common/path.py
bamboo/common/profile.py
bamboo/common/status.py
bamboo/coot_utils/__init__.py
bamboo/coot_utils/scripts.py
bamboo/coot_utils/utils.py
bamboo/html/__init__.py
bamboo/html/builder.py
bamboo/html/div.py
bamboo/html/section.py
bamboo/maths/__init__.py
bamboo/maths/angles.py
bamboo/plot/__init__.py
bamboo/plot/bar.py
bamboo/plot/radar.py
bamboo/plot/simple.py
bamboo/plot/tree.py
bamboo/pymol_utils/__init__.py
bamboo/pymol_utils/shapes.py
bamboo/rdkit_utils/__init__.py
bamboo/rdkit_utils/mol.py
bamboo/rdkit_utils/smile.py
bamboo/rdkit_utils/bonds/__init__.py
bamboo/rdkit_utils/bonds/dihedral.py
bamboo/rdkit_utils/bonds/fragment.py
bamboo/rdkit_utils/bonds/rotate.py
bamboo/rdkit_utils/contacts/__init__.py
bamboo/rdkit_utils/contacts/utils.py
bamboo/rdkit_utils/coords/__init__.py
bamboo/rdkit_utils/coords/coords.py
bamboo/rdkit_utils/coords/fragment.py
bamboo/rdkit_utils/coords/utils.py
bamboo/regression/__init__.py
bamboo/regression/resources/__init__.py
bamboo/resources/__init__.py
bamboo/stats/__init__.py
bamboo/stats/cluster.py
bamboo/stats/networks.py
bamboo/stats/ospina.py
bamboo/stats/statistical_tests.py
bamboo/stats/utils.py
bamboo/wrappers/__init__.py
bamboo/wrappers/mlfsom.py
bamboo/wrappers/ligand_builders/__init__.py
bamboo/wrappers/ligand_builders/elbow.py
bamboo/wrappers/ligand_builders/grade.py
bamboo/wrappers/ligand_builders/prodrg.py
bamboo/wrappers/ligand_builders/writedict.py
bamboo/wrappers/ligand_fitters/__init__.py
bamboo/wrappers/ligand_fitters/arpwarp.py
bamboo/wrappers/ligand_fitters/flynn.py
bamboo/wrappers/ligand_fitters/ligandfit.py
bamboo/wrappers/ligand_fitters/rhofit.py
pandda_2-0.0.3.dist-info/METADATA
pandda_2-0.0.3.dist-info/WHEEL
pandda_2-0.0.3.dist-info/top_level.txt
pandda_2-0.0.3.dist-info/RECORD
