Metadata-Version: 2.1
Name: pandda-2
Version: 0.0.3
Summary: A package for handling many crystalographic datasets simultainiously
Home-page: https://github.com/pypa/sampleproject
Author: Conor Francis Wild
Author-email: conor.wild@sky.com
License: UNKNOWN
Platform: UNKNOWN
Classifier: Programming Language :: Python :: 2
Classifier: License :: OSI Approved :: MIT License
Classifier: Operating System :: OS Independent
Requires-Python: >=2.7
Requires-Dist: joblib
Requires-Dist: luigi
Requires-Dist: pathlib
Requires-Dist: configparser
Requires-Dist: constants
Requires-Dist: dask
Requires-Dist: cloudpickle
Requires-Dist: biopandas (==0.2.4)
